{
    "os": "Linux-6.2.0-32-generic-x86_64-with-glibc2.10",
    "python": "3.8.18",
    "heartbeatAt": "2023-10-31T12:27:02.406815",
    "startedAt": "2023-10-31T12:27:01.656959",
    "docker": null,
    "cuda": null,
    "args": [],
    "state": "running",
    "program": "main.py",
    "codePathLocal": "main.py",
    "codePath": "main.py",
    "git": {
        "remote": "git@github.com:BlackCetus/bachelor.git",
        "commit": "465df6b4c8269893f6802e019105bafa617ec041"
    },
    "email": "ge28jer@mytum.de",
    "root": "/nfs/home/students/t.reim/bachelor/pytorchtest",
    "host": "gpu02.exbio.wzw.tum.de",
    "username": "t.reim",
    "executable": "/nfs/home/students/t.reim/.conda/envs/mamba2/bin/python",
    "cpu_count": 64,
    "cpu_count_logical": 64,
    "cpu_freq": {
        "current": 2516.0329843750005,
        "min": 0.0,
        "max": 0.0
    },
    "cpu_freq_per_core": [
        {
            "current": 2345.703,
            "min": 0.0,
            "max": 0.0
        },
        {
            "current": 2345.703,
            "min": 0.0,
            "max": 0.0
        },
        {
            "current": 3330.515,
            "min": 0.0,
            "max": 0.0
        },
        {
            "current": 3336.761,
            "min": 0.0,
            "max": 0.0
        },
        {
            "current": 2345.703,
            "min": 0.0,
            "max": 0.0
        },
        {
            "current": 2345.703,
            "min": 0.0,
            "max": 0.0
        },
        {
            "current": 2345.703,
            "min": 0.0,
            "max": 0.0
        },
        {
            "current": 2345.703,
            "min": 0.0,
            "max": 0.0
        },
        {
            "current": 2345.703,
            "min": 0.0,
            "max": 0.0
        },
        {
            "current": 2345.703,
            "min": 0.0,
            "max": 0.0
        },
        {
            "current": 2345.703,
            "min": 0.0,
            "max": 0.0
        },
        {
            "current": 2345.703,
            "min": 0.0,
            "max": 0.0
        },
        {
            "current": 2345.703,
            "min": 0.0,
            "max": 0.0
        },
        {
            "current": 2345.703,
            "min": 0.0,
            "max": 0.0
        },
        {
            "current": 2345.703,
            "min": 0.0,
            "max": 0.0
        },
        {
            "current": 2345.703,
            "min": 0.0,
            "max": 0.0
        },
        {
            "current": 2345.703,
            "min": 0.0,
            "max": 0.0
        },
        {
            "current": 2345.703,
            "min": 0.0,
            "max": 0.0
        },
        {
            "current": 2345.703,
            "min": 0.0,
            "max": 0.0
        },
        {
            "current": 2345.703,
            "min": 0.0,
            "max": 0.0
        },
        {
            "current": 2345.703,
            "min": 0.0,
            "max": 0.0
        },
        {
            "current": 2345.703,
            "min": 0.0,
            "max": 0.0
        },
        {
            "current": 2345.703,
            "min": 0.0,
            "max": 0.0
        },
        {
            "current": 2345.703,
            "min": 0.0,
            "max": 0.0
        },
        {
            "current": 2345.703,
            "min": 0.0,
            "max": 0.0
        },
        {
            "current": 2345.703,
            "min": 0.0,
            "max": 0.0
        },
        {
            "current": 2345.703,
            "min": 0.0,
            "max": 0.0
        },
        {
            "current": 2345.703,
            "min": 0.0,
            "max": 0.0
        },
        {
            "current": 3341.271,
            "min": 0.0,
            "max": 0.0
        },
        {
            "current": 2345.703,
            "min": 0.0,
            "max": 0.0
        },
        {
            "current": 2345.703,
            "min": 0.0,
            "max": 0.0
        },
        {
            "current": 2345.703,
            "min": 0.0,
            "max": 0.0
        },
        {
            "current": 2588.4,
            "min": 0.0,
            "max": 0.0
        },
        {
            "current": 2345.703,
            "min": 0.0,
            "max": 0.0
        },
        {
            "current": 3082.284,
            "min": 0.0,
            "max": 0.0
        },
        {
            "current": 2345.703,
            "min": 0.0,
            "max": 0.0
        },
        {
            "current": 2191.97,
            "min": 0.0,
            "max": 0.0
        },
        {
            "current": 2345.703,
            "min": 0.0,
            "max": 0.0
        },
        {
            "current": 2345.703,
            "min": 0.0,
            "max": 0.0
        },
        {
            "current": 2345.703,
            "min": 0.0,
            "max": 0.0
        },
        {
            "current": 3273.582,
            "min": 0.0,
            "max": 0.0
        },
        {
            "current": 2483.698,
            "min": 0.0,
            "max": 0.0
        },
        {
            "current": 3345.239,
            "min": 0.0,
            "max": 0.0
        },
        {
            "current": 3347.34,
            "min": 0.0,
            "max": 0.0
        },
        {
            "current": 2833.799,
            "min": 0.0,
            "max": 0.0
        },
        {
            "current": 2345.703,
            "min": 0.0,
            "max": 0.0
        },
        {
            "current": 2345.703,
            "min": 0.0,
            "max": 0.0
        },
        {
            "current": 2345.703,
            "min": 0.0,
            "max": 0.0
        },
        {
            "current": 2345.703,
            "min": 0.0,
            "max": 0.0
        },
        {
            "current": 2345.703,
            "min": 0.0,
            "max": 0.0
        },
        {
            "current": 2345.703,
            "min": 0.0,
            "max": 0.0
        },
        {
            "current": 1734.336,
            "min": 0.0,
            "max": 0.0
        },
        {
            "current": 2345.703,
            "min": 0.0,
            "max": 0.0
        },
        {
            "current": 2345.703,
            "min": 0.0,
            "max": 0.0
        },
        {
            "current": 2345.703,
            "min": 0.0,
            "max": 0.0
        },
        {
            "current": 2345.703,
            "min": 0.0,
            "max": 0.0
        },
        {
            "current": 2345.703,
            "min": 0.0,
            "max": 0.0
        },
        {
            "current": 3340.28,
            "min": 0.0,
            "max": 0.0
        },
        {
            "current": 3337.693,
            "min": 0.0,
            "max": 0.0
        },
        {
            "current": 2345.703,
            "min": 0.0,
            "max": 0.0
        },
        {
            "current": 2345.703,
            "min": 0.0,
            "max": 0.0
        },
        {
            "current": 2345.703,
            "min": 0.0,
            "max": 0.0
        },
        {
            "current": 2345.703,
            "min": 0.0,
            "max": 0.0
        },
        {
            "current": 2345.703,
            "min": 0.0,
            "max": 0.0
        }
    ],
    "disk": {
        "/": {
            "total": 548.0470123291016,
            "used": 35.39780044555664
        }
    },
    "gpu": "NVIDIA A40",
    "gpu_count": 3,
    "gpu_devices": [
        {
            "name": "NVIDIA A40",
            "memory_total": 48305799168
        },
        {
            "name": "NVIDIA A40",
            "memory_total": 48305799168
        },
        {
            "name": "NVIDIA A40",
            "memory_total": 48305799168
        }
    ],
    "memory": {
        "total": 503.4728889465332
    }
}
